{"id": 1589, "companyId": 79, "companyName": "마스터키 전주고사점", "companyTel": "063-288-8782", "companyHomepage": "http://www.master-key.co.kr/booking/bk_detail?bid=8", "title": "인디아나 존스", "intro": " 마지막 모험후 자신이 재직중인 바네트 대학으로 돌아온 박사는 몇달간 비워두었던 개학 연구실에서 오래전에 도착한 소포를 발견하였다.\n소포중에는 아버지의 일기장 등이 있었다. 아버지의 흔적을 쫓는 도중 존슨박사는 우연히 만난 월터도노반에게서 아버지에 관련된 단서를 얻는다.\n도노반은 자신이 앙카라 북쪽에서 발견한 반쪽자리 신의 석판 탁폰을 보여주며 헨리박사의 일기장을 참고로 나머지 반쪽 석판과 예수가 최후의 만찬때 사용했다는 술장'성배'를 찾아달라고 부탁하는데...", "category": "추리", "typeOnly": false, "typeDifferent": false, "typeNew": false, "level": 3, "recommendPerson": 4, "tool": "낮음", "activity": "낮음", "time": 60, "grade": 3.1, "thumbnail": "https://roomescape-backend-image.s3.ap-northeast-2.amazonaws.com/theme/0397f263-d9a8-4410-8f9f-a3023bc08bc4.jpg", "reviewCount": 50, "wishCount": 7, "isWish": false, "images": [], "themePrices": [], "isReview": false, "address": "전북 전주시 완산구 전주객사5길 30-2", "addressDetail": "", "active": true, "main": false, "sortCode": 0, "review_list": [{"id": 824234, "themeId": 1589, "userId": 2914, "reviewLevel": 8, "userName": "검정젤리", "playDate": "2023-09-29", "grade": 2, "level": "쉬움", "success": "성공", "extraTime": "46:50", "remainingTime": "13:10", "userHint": 0, "content": "1862방\n2인 with 붕붕", "isGrade": true, "createdAt": "09/29", "company": {"id": 79, "title": "마스터키 전주고사점", "isWish": false, "distance": 0, "createdAt": "2023-10-31"}, "theme": {"id": 1589, "companyName": "마스터키 전주고사점", "title": "인디아나 존스", "category": "추리", "time": 60, "thumbnail": "https://roomescape-backend-image.s3.ap-northeast-2.amazonaws.com/theme/0397f263-d9a8-4410-8f9f-a3023bc08bc4.jpg", "isWish": false, "isReview": false, "address": "전북 전주시 완산구 전주객사5길 30-2", "addressDetail": ""}, "comments": [], "likeCount": 0, "isLike": false, "reportCount": 0}, {"id": 824148, "themeId": 1589, "userId": 4343, "reviewLevel": 8, "userName": "붕붕", "playDate": "2023-09-29", "grade": 2, "level": "보통", "success": "성공", "extraTime": "46:50", "remainingTime": "13:10", "userHint": 0, "content": "2인", "isGrade": true, "createdAt": "09/29", "company": {"id": 79, "title": "마스터키 전주고사점", "isWish": false, "distance": 0, "createdAt": "2023-10-31"}, "theme": {"id": 1589, "companyName": "마스터키 전주고사점", "title": "인디아나 존스", "category": "추리", "time": 60, "thumbnail": "https://roomescape-backend-image.s3.ap-northeast-2.amazonaws.com/theme/0397f263-d9a8-4410-8f9f-a3023bc08bc4.jpg", "isWish": false, "isReview": false, "address": "전북 전주시 완산구 전주객사5길 30-2", "addressDetail": ""}, "comments": [], "likeCount": 0, "isLike": false, "reportCount": 0}, {"id": 788066, "themeId": 1589, "userId": 5355, "reviewLevel": 6, "userName": "지눙", "playDate": "2023-08-09", "grade": 0, "level": "매우쉬움", "success": "성공", "extraTime": "06:17", "remainingTime": "53:43", "userHint": 0, "content": "191. 2인 전주연방", "isGrade": false, "createdAt": "08/09", "company": {"id": 79, "title": "마스터키 전주고사점", "isWish": false, "distance": 0, "createdAt": "2023-10-31"}, "theme": {"id": 1589, "companyName": "마스터키 전주고사점", "title": "인디아나 존스", "category": "추리", "time": 60, "thumbnail": "https://roomescape-backend-image.s3.ap-northeast-2.amazonaws.com/theme/0397f263-d9a8-4410-8f9f-a3023bc08bc4.jpg", "isWish": false, "isReview": false, "address": "전북 전주시 완산구 전주객사5길 30-2", "addressDetail": ""}, "comments": [], "likeCount": 0, "isLike": false, "reportCount": 0}, {"id": 782807, "themeId": 1589, "userId": 48043, "reviewLevel": 1, "userName": "호호할하", "playDate": "2023-06-03", "grade": 4, "level": "쉬움", "success": "성공", "extraTime": null, "remainingTime": null, "userHint": null, "content": "기록용", "isGrade": true, "createdAt": "08/01", "company": {"id": 79, "title": "마스터키 전주고사점", "isWish": false, "distance": 0, "createdAt": "2023-10-31"}, "theme": {"id": 1589, "companyName": "마스터키 전주고사점", "title": "인디아나 존스", "category": "추리", "time": 60, "thumbnail": "https://roomescape-backend-image.s3.ap-northeast-2.amazonaws.com/theme/0397f263-d9a8-4410-8f9f-a3023bc08bc4.jpg", "isWish": false, "isReview": false, "address": "전북 전주시 완산구 전주객사5길 30-2", "addressDetail": ""}, "comments": [], "likeCount": 0, "isLike": false, "reportCount": 0}, {"id": 745428, "themeId": 1589, "userId": 41229, "reviewLevel": 2, "userName": "노란도토리", "playDate": "2023-06-03", "grade": 5, "level": "매우쉬움", "success": "성공", "extraTime": null, "remainingTime": null, "userHint": null, "content": "기록용", "isGrade": true, "createdAt": "06/03", "company": {"id": 79, "title": "마스터키 전주고사점", "isWish": false, "distance": 0, "createdAt": "2023-10-31"}, "theme": {"id": 1589, "companyName": "마스터키 전주고사점", "title": "인디아나 존스", "category": "추리", "time": 60, "thumbnail": "https://roomescape-backend-image.s3.ap-northeast-2.amazonaws.com/theme/0397f263-d9a8-4410-8f9f-a3023bc08bc4.jpg", "isWish": false, "isReview": false, "address": "전북 전주시 완산구 전주객사5길 30-2", "addressDetail": ""}, "comments": [], "likeCount": 0, "isLike": false, "reportCount": 0}, {"id": 742989, "themeId": 1589, "userId": 43766, "reviewLevel": 2, "userName": "야도르", "playDate": "2023-05-30", "grade": 5, "level": "매우쉬움", "success": "성공", "extraTime": null, "remainingTime": null, "userHint": null, "content": "기록", "isGrade": true, "createdAt": "05/30", "company": {"id": 79, "title": "마스터키 전주고사점", "isWish": false, "distance": 0, "createdAt": "2023-10-31"}, "theme": {"id": 1589, "companyName": "마스터키 전주고사점", "title": "인디아나 존스", "category": "추리", "time": 60, "thumbnail": "https://roomescape-backend-image.s3.ap-northeast-2.amazonaws.com/theme/0397f263-d9a8-4410-8f9f-a3023bc08bc4.jpg", "isWish": false, "isReview": false, "address": "전북 전주시 완산구 전주객사5길 30-2", "addressDetail": ""}, "comments": [], "likeCount": 0, "isLike": false, "reportCount": 0}, {"id": 698747, "themeId": 1589, "userId": 3631, "reviewLevel": 8, "userName": "파인", "playDate": "2023-03-25", "grade": 2.5, "level": "보통", "success": "성공", "extraTime": "47:00", "remainingTime": "13:00", "userHint": 0, "content": "3인", "isGrade": true, "createdAt": "03/25", "company": {"id": 79, "title": "마스터키 전주고사점", "isWish": false, "distance": 0, "createdAt": "2023-10-31"}, "theme": {"id": 1589, "companyName": "마스터키 전주고사점", "title": "인디아나 존스", "category": "추리", "time": 60, "thumbnail": "https://roomescape-backend-image.s3.ap-northeast-2.amazonaws.com/theme/0397f263-d9a8-4410-8f9f-a3023bc08bc4.jpg", "isWish": false, "isReview": false, "address": "전북 전주시 완산구 전주객사5길 30-2", "addressDetail": ""}, "comments": [], "likeCount": 0, "isLike": false, "reportCount": 0}, {"id": 691935, "themeId": 1589, "userId": 362, "reviewLevel": 8, "userName": "미미1", "playDate": "2023-03-13", "grade": 0, "level": "쉬움", "success": "성공", "extraTime": "47:19", "remainingTime": "12:41", "userHint": 0, "content": "3인", "isGrade": false, "createdAt": "03/13", "company": {"id": 79, "title": "마스터키 전주고사점", "isWish": false, "distance": 0, "createdAt": "2023-10-31"}, "theme": {"id": 1589, "companyName": "마스터키 전주고사점", "title": "인디아나 존스", "category": "추리", "time": 60, "thumbnail": "https://roomescape-backend-image.s3.ap-northeast-2.amazonaws.com/theme/0397f263-d9a8-4410-8f9f-a3023bc08bc4.jpg", "isWish": false, "isReview": false, "address": "전북 전주시 완산구 전주객사5길 30-2", "addressDetail": ""}, "comments": [], "likeCount": 0, "isLike": false, "reportCount": 0}, {"id": 691729, "themeId": 1589, "userId": 75, "reviewLevel": 8, "userName": "슬기로운", "playDate": "2023-03-12", "grade": 3, "level": "쉬움", "success": "성공", "extraTime": "47:19", "remainingTime": "12:41", "userHint": 0, "content": "1535\n3인", "isGrade": true, "createdAt": "03/12", "company": {"id": 79, "title": "마스터키 전주고사점", "isWish": false, "distance": 0, "createdAt": "2023-10-31"}, "theme": {"id": 1589, "companyName": "마스터키 전주고사점", "title": "인디아나 존스", "category": "추리", "time": 60, "thumbnail": "https://roomescape-backend-image.s3.ap-northeast-2.amazonaws.com/theme/0397f263-d9a8-4410-8f9f-a3023bc08bc4.jpg", "isWish": false, "isReview": false, "address": "전북 전주시 완산구 전주객사5길 30-2", "addressDetail": ""}, "comments": [], "likeCount": 0, "isLike": false, "reportCount": 0}, {"id": 660195, "themeId": 1589, "userId": 30168, "reviewLevel": 2, "userName": "수연하", "playDate": "2023-01-20", "grade": 3.5, "level": "쉬움", "success": "성공", "extraTime": null, "remainingTime": null, "userHint": 1, "content": "3인플레이\n나름 재밌음", "isGrade": true, "createdAt": "01/20", "company": {"id": 79, "title": "마스터키 전주고사점", "isWish": false, "distance": 0, "createdAt": "2023-10-31"}, "theme": {"id": 1589, "companyName": "마스터키 전주고사점", "title": "인디아나 존스", "category": "추리", "time": 60, "thumbnail": "https://roomescape-backend-image.s3.ap-northeast-2.amazonaws.com/theme/0397f263-d9a8-4410-8f9f-a3023bc08bc4.jpg", "isWish": false, "isReview": false, "address": "전북 전주시 완산구 전주객사5길 30-2", "addressDetail": ""}, "comments": [], "likeCount": 0, "isLike": false, "reportCount": 0}, {"id": 633343, "themeId": 1589, "userId": 25411, "reviewLevel": 3, "userName": "도하", "playDate": "2022-12-09", "grade": 3.5, "level": "매우쉬움", "success": "성공", "extraTime": "43:00", "remainingTime": "17:00", "userHint": 0, "content": "2인 클리어", "isGrade": true, "createdAt": "12/09", "company": {"id": 79, "title": "마스터키 전주고사점", "isWish": false, "distance": 0, "createdAt": "2023-10-31"}, "theme": {"id": 1589, "companyName": "마스터키 전주고사점", "title": "인디아나 존스", "category": "추리", "time": 60, "thumbnail": "https://roomescape-backend-image.s3.ap-northeast-2.amazonaws.com/theme/0397f263-d9a8-4410-8f9f-a3023bc08bc4.jpg", "isWish": false, "isReview": false, "address": "전북 전주시 완산구 전주객사5길 30-2", "addressDetail": ""}, "comments": [], "likeCount": 0, "isLike": false, "reportCount": 0}, {"id": 598664, "themeId": 1589, "userId": 632, "reviewLevel": 8, "userName": "레콤", "playDate": "2021-02-25", "grade": 0, "level": "보통", "success": "성공", "extraTime": "18:22", "remainingTime": "41:38", "userHint": 0, "content": " ", "isGrade": false, "createdAt": "10/14", "company": {"id": 79, "title": "마스터키 전주고사점", "isWish": false, "distance": 0, "createdAt": "2023-10-31"}, "theme": {"id": 1589, "companyName": "마스터키 전주고사점", "title": "인디아나 존스", "category": "추리", "time": 60, "thumbnail": "https://roomescape-backend-image.s3.ap-northeast-2.amazonaws.com/theme/0397f263-d9a8-4410-8f9f-a3023bc08bc4.jpg", "isWish": false, "isReview": false, "address": "전북 전주시 완산구 전주객사5길 30-2", "addressDetail": ""}, "comments": [], "likeCount": 0, "isLike": false, "reportCount": 0}, {"id": 597141, "themeId": 1589, "userId": 26113, "reviewLevel": 1, "userName": "신동엽이", "playDate": "2022-10-11", "grade": 5, "level": "매우쉬움", "success": "성공", "extraTime": null, "remainingTime": null, "userHint": 0, "content": "쉽고재밌", "isGrade": true, "createdAt": "10/11", "company": {"id": 79, "title": "마스터키 전주고사점", "isWish": false, "distance": 0, "createdAt": "2023-10-31"}, "theme": {"id": 1589, "companyName": "마스터키 전주고사점", "title": "인디아나 존스", "category": "추리", "time": 60, "thumbnail": "https://roomescape-backend-image.s3.ap-northeast-2.amazonaws.com/theme/0397f263-d9a8-4410-8f9f-a3023bc08bc4.jpg", "isWish": false, "isReview": false, "address": "전북 전주시 완산구 전주객사5길 30-2", "addressDetail": ""}, "comments": [], "likeCount": 0, "isLike": false, "reportCount": 0}, {"id": 587035, "themeId": 1589, "userId": 19137, "reviewLevel": 4, "userName": "두왕", "playDate": "2022-09-27", "grade": 3.5, "level": "보통", "success": "성공", "extraTime": "04:00", "remainingTime": "56:00", "userHint": 3, "content": "의도치않게 두 번 플레이했는데 처음엔 못 깨고 두번째에 클리어.", "isGrade": true, "createdAt": "09/27", "company": {"id": 79, "title": "마스터키 전주고사점", "isWish": false, "distance": 0, "createdAt": "2023-10-31"}, "theme": {"id": 1589, "companyName": "마스터키 전주고사점", "title": "인디아나 존스", "category": "추리", "time": 60, "thumbnail": "https://roomescape-backend-image.s3.ap-northeast-2.amazonaws.com/theme/0397f263-d9a8-4410-8f9f-a3023bc08bc4.jpg", "isWish": false, "isReview": false, "address": "전북 전주시 완산구 전주객사5길 30-2", "addressDetail": ""}, "comments": [], "likeCount": 0, "isLike": false, "reportCount": 0}, {"id": 562538, "themeId": 1589, "userId": 20603, "reviewLevel": 2, "userName": "하유", "playDate": "2022-08-19", "grade": 5, "level": "매우쉬움", "success": "성공", "extraTime": null, "remainingTime": null, "userHint": null, "content": "기록", "isGrade": true, "createdAt": "08/19", "company": {"id": 79, "title": "마스터키 전주고사점", "isWish": false, "distance": 0, "createdAt": "2023-10-31"}, "theme": {"id": 1589, "companyName": "마스터키 전주고사점", "title": "인디아나 존스", "category": "추리", "time": 60, "thumbnail": "https://roomescape-backend-image.s3.ap-northeast-2.amazonaws.com/theme/0397f263-d9a8-4410-8f9f-a3023bc08bc4.jpg", "isWish": false, "isReview": false, "address": "전북 전주시 완산구 전주객사5길 30-2", "addressDetail": ""}, "comments": [], "likeCount": 0, "isLike": false, "reportCount": 0}, {"id": 531081, "themeId": 1589, "userId": 14850, "reviewLevel": 2, "userName": "dlsgn486", "playDate": "2022-06-27", "grade": 2.5, "level": "쉬움", "success": "성공", "extraTime": "10:20", "remainingTime": "49:40", "userHint": null, "content": "2인", "isGrade": true, "createdAt": "06/27", "company": {"id": 79, "title": "마스터키 전주고사점", "isWish": false, "distance": 0, "createdAt": "2023-10-31"}, "theme": {"id": 1589, "companyName": "마스터키 전주고사점", "title": "인디아나 존스", "category": "추리", "time": 60, "thumbnail": "https://roomescape-backend-image.s3.ap-northeast-2.amazonaws.com/theme/0397f263-d9a8-4410-8f9f-a3023bc08bc4.jpg", "isWish": false, "isReview": false, "address": "전북 전주시 완산구 전주객사5길 30-2", "addressDetail": ""}, "comments": [], "likeCount": 0, "isLike": false, "reportCount": 0}, {"id": 472494, "themeId": 1589, "userId": 12470, "reviewLevel": 1, "userName": "볼", "playDate": "2022-03-18", "grade": 2, "level": "쉬움", "success": "성공", "extraTime": "29:00", "remainingTime": "31:00", "userHint": null, "content": "너무 쉬웠음 3명이서 처음으로 해봤는데 30분정도만에 탈출 함", "isGrade": true, "createdAt": "03/18", "company": {"id": 79, "title": "마스터키 전주고사점", "isWish": false, "distance": 0, "createdAt": "2023-10-31"}, "theme": {"id": 1589, "companyName": "마스터키 전주고사점", "title": "인디아나 존스", "category": "추리", "time": 60, "thumbnail": "https://roomescape-backend-image.s3.ap-northeast-2.amazonaws.com/theme/0397f263-d9a8-4410-8f9f-a3023bc08bc4.jpg", "isWish": false, "isReview": false, "address": "전북 전주시 완산구 전주객사5길 30-2", "addressDetail": ""}, "comments": [], "likeCount": 0, "isLike": false, "reportCount": 0}, {"id": 468388, "themeId": 1589, "userId": 11569, "reviewLevel": 2, "userName": "GRT회장", "playDate": "2022-03-10", "grade": 2.5, "level": "매우쉬움", "success": "성공", "extraTime": "00:00", "remainingTime": "60:00", "userHint": null, "content": "#8. 2022년 1월 2일 청주에 이은 2번째 원정인 전주에서 플레이함. 우리 앞타임에 초딩 2명이서 클리어하는 것을 보고 자신감이 뿜뿜해서 시작하였다. 강남의 자본이 빵빵하게 들어간 최신 방탈출에 비해서는 인테리어나 소품의 퀄리티가 부족하지만, 테마와 나름대로 잘 어우러져 있는 것은 장점이다. 이 방탈출은 적당한 활동성도 있고 초심자들이 즐기기 좋지만 가장 큰 단점은 볼륨이 부족하다는 점이다. 우리는 8번째 방탈출 도전이었는데 힌트를 쓰지 않고 25분 넘게 남기고 탈출에 성공했음. 안에서 2문제 정도 고민하면서 시간을 소비하였는데도 이렇게 시간이 남았으니, 방이 2-3개 정도 더 있었다면 만족도가 크게 높았을거 같음. 어린 친구들이나 일행이 모두 초심자라면 강력 추천함.", "isGrade": true, "createdAt": "03/10", "company": {"id": 79, "title": "마스터키 전주고사점", "isWish": false, "distance": 0, "createdAt": "2023-10-31"}, "theme": {"id": 1589, "companyName": "마스터키 전주고사점", "title": "인디아나 존스", "category": "추리", "time": 60, "thumbnail": "https://roomescape-backend-image.s3.ap-northeast-2.amazonaws.com/theme/0397f263-d9a8-4410-8f9f-a3023bc08bc4.jpg", "isWish": false, "isReview": false, "address": "전북 전주시 완산구 전주객사5길 30-2", "addressDetail": ""}, "comments": [], "likeCount": 0, "isLike": false, "reportCount": 0}, {"id": 418730, "themeId": 1589, "userId": 11029, "reviewLevel": 2, "userName": "션션", "playDate": "2021-12-21", "grade": 2.5, "level": "쉬움", "success": "성공", "extraTime": null, "remainingTime": null, "userHint": null, "content": "기록", "isGrade": true, "createdAt": "12/21", "company": {"id": 79, "title": "마스터키 전주고사점", "isWish": false, "distance": 0, "createdAt": "2023-10-31"}, "theme": {"id": 1589, "companyName": "마스터키 전주고사점", "title": "인디아나 존스", "category": "추리", "time": 60, "thumbnail": "https://roomescape-backend-image.s3.ap-northeast-2.amazonaws.com/theme/0397f263-d9a8-4410-8f9f-a3023bc08bc4.jpg", "isWish": false, "isReview": false, "address": "전북 전주시 완산구 전주객사5길 30-2", "addressDetail": ""}, "comments": [], "likeCount": 0, "isLike": false, "reportCount": 0}, {"id": 398639, "themeId": 1589, "userId": 592, "reviewLevel": 6, "userName": "써노", "playDate": "2021-11-10", "grade": 3, "level": "매우쉬움", "success": "성공", "extraTime": "47:20", "remainingTime": "12:40", "userHint": 0, "content": "예아~ 관찰력에서 시간 씀", "isGrade": true, "createdAt": "11/10", "company": {"id": 79, "title": "마스터키 전주고사점", "isWish": false, "distance": 0, "createdAt": "2023-10-31"}, "theme": {"id": 1589, "companyName": "마스터키 전주고사점", "title": "인디아나 존스", "category": "추리", "time": 60, "thumbnail": "https://roomescape-backend-image.s3.ap-northeast-2.amazonaws.com/theme/0397f263-d9a8-4410-8f9f-a3023bc08bc4.jpg", "isWish": false, "isReview": false, "address": "전북 전주시 완산구 전주객사5길 30-2", "addressDetail": ""}, "comments": [], "likeCount": 0, "isLike": false, "reportCount": 0}, {"id": 392704, "themeId": 1589, "userId": 561, "reviewLevel": 8, "userName": "퓨퓨", "playDate": "2021-10-28", "grade": 3, "level": "쉬움", "success": "성공", "extraTime": "47:00", "remainingTime": "13:00", "userHint": 0, "content": "1107. 신촌에서도 했는데 훨씬 관리잘되어있고 깔끔했음. 문제수는 더 적어진 느낌?무난하고 재밌음", "isGrade": true, "createdAt": "10/28", "company": {"id": 79, "title": "마스터키 전주고사점", "isWish": false, "distance": 0, "createdAt": "2023-10-31"}, "theme": {"id": 1589, "companyName": "마스터키 전주고사점", "title": "인디아나 존스", "category": "추리", "time": 60, "thumbnail": "https://roomescape-backend-image.s3.ap-northeast-2.amazonaws.com/theme/0397f263-d9a8-4410-8f9f-a3023bc08bc4.jpg", "isWish": false, "isReview": false, "address": "전북 전주시 완산구 전주객사5길 30-2", "addressDetail": ""}, "comments": [], "likeCount": 0, "isLike": false, "reportCount": 0}, {"id": 350368, "themeId": 1589, "userId": 2155, "reviewLevel": 8, "userName": "뻐꾹", "playDate": "2021-08-15", "grade": 3.5, "level": "쉬움", "success": "성공", "extraTime": "12:30", "remainingTime": "47:30", "userHint": 0, "content": "혼방) 관찰력이 상당히 필요한 테마", "isGrade": true, "createdAt": "08/15", "company": {"id": 79, "title": "마스터키 전주고사점", "isWish": false, "distance": 0, "createdAt": "2023-10-31"}, "theme": {"id": 1589, "companyName": "마스터키 전주고사점", "title": "인디아나 존스", "category": "추리", "time": 60, "thumbnail": "https://roomescape-backend-image.s3.ap-northeast-2.amazonaws.com/theme/0397f263-d9a8-4410-8f9f-a3023bc08bc4.jpg", "isWish": false, "isReview": false, "address": "전북 전주시 완산구 전주객사5길 30-2", "addressDetail": ""}, "comments": [], "likeCount": 0, "isLike": false, "reportCount": 0}, {"id": 347239, "themeId": 1589, "userId": 7818, "reviewLevel": 6, "userName": "Hyun", "playDate": "2021-08-11", "grade": 3.5, "level": "쉬움", "success": "성공", "extraTime": "13:15", "remainingTime": "46:45", "userHint": 2, "content": "", "isGrade": true, "createdAt": "08/11", "company": {"id": 79, "title": "마스터키 전주고사점", "isWish": false, "distance": 0, "createdAt": "2023-10-31"}, "theme": {"id": 1589, "companyName": "마스터키 전주고사점", "title": "인디아나 존스", "category": "추리", "time": 60, "thumbnail": "https://roomescape-backend-image.s3.ap-northeast-2.amazonaws.com/theme/0397f263-d9a8-4410-8f9f-a3023bc08bc4.jpg", "isWish": false, "isReview": false, "address": "전북 전주시 완산구 전주객사5길 30-2", "addressDetail": ""}, "comments": [], "likeCount": 0, "isLike": false, "reportCount": 0}, {"id": 341245, "themeId": 1589, "userId": 9065, "reviewLevel": 2, "userName": "전주방린이", "playDate": "2021-08-02", "grade": 0, "level": "쉬움", "success": "성공", "extraTime": "10:00", "remainingTime": "50:00", "userHint": null, "content": "방린이가 하기엔 딱인 난이도", "isGrade": false, "createdAt": "08/02", "company": {"id": 79, "title": "마스터키 전주고사점", "isWish": false, "distance": 0, "createdAt": "2023-10-31"}, "theme": {"id": 1589, "companyName": "마스터키 전주고사점", "title": "인디아나 존스", "category": "추리", "time": 60, "thumbnail": "https://roomescape-backend-image.s3.ap-northeast-2.amazonaws.com/theme/0397f263-d9a8-4410-8f9f-a3023bc08bc4.jpg", "isWish": false, "isReview": false, "address": "전북 전주시 완산구 전주객사5길 30-2", "addressDetail": ""}, "comments": [], "likeCount": 0, "isLike": false, "reportCount": 0}, {"id": 337576, "themeId": 1589, "userId": 2392, "reviewLevel": 6, "userName": "사슴신", "playDate": "2021-07-27", "grade": 0, "level": "쉬움", "success": "성공", "extraTime": null, "remainingTime": null, "userHint": null, "content": ".", "isGrade": false, "createdAt": "07/27", "company": {"id": 79, "title": "마스터키 전주고사점", "isWish": false, "distance": 0, "createdAt": "2023-10-31"}, "theme": {"id": 1589, "companyName": "마스터키 전주고사점", "title": "인디아나 존스", "category": "추리", "time": 60, "thumbnail": "https://roomescape-backend-image.s3.ap-northeast-2.amazonaws.com/theme/0397f263-d9a8-4410-8f9f-a3023bc08bc4.jpg", "isWish": false, "isReview": false, "address": "전북 전주시 완산구 전주객사5길 30-2", "addressDetail": ""}, "comments": [], "likeCount": 0, "isLike": false, "reportCount": 0}, {"id": 312443, "themeId": 1589, "userId": 6609, "reviewLevel": 1, "userName": "방탈러리즈", "playDate": "2021-06-11", "grade": 2, "level": "쉬움", "success": "성공", "extraTime": "12:00", "remainingTime": "48:00", "userHint": null, "content": "쉽다", "isGrade": true, "createdAt": "06/11", "company": {"id": 79, "title": "마스터키 전주고사점", "isWish": false, "distance": 0, "createdAt": "2023-10-31"}, "theme": {"id": 1589, "companyName": "마스터키 전주고사점", "title": "인디아나 존스", "category": "추리", "time": 60, "thumbnail": "https://roomescape-backend-image.s3.ap-northeast-2.amazonaws.com/theme/0397f263-d9a8-4410-8f9f-a3023bc08bc4.jpg", "isWish": false, "isReview": false, "address": "전북 전주시 완산구 전주객사5길 30-2", "addressDetail": ""}, "comments": [], "likeCount": 0, "isLike": false, "reportCount": 0}, {"id": 291249, "themeId": 1589, "userId": 7737, "reviewLevel": 2, "userName": "청새", "playDate": "2021-05-06", "grade": 5, "level": "쉬움", "success": "성공", "extraTime": null, "remainingTime": null, "userHint": null, "content": "2인 방린이끼리가서 뚝딱뚝딱 깨기 쉬운 정도인 테마", "isGrade": true, "createdAt": "05/06", "company": {"id": 79, "title": "마스터키 전주고사점", "isWish": false, "distance": 0, "createdAt": "2023-10-31"}, "theme": {"id": 1589, "companyName": "마스터키 전주고사점", "title": "인디아나 존스", "category": "추리", "time": 60, "thumbnail": "https://roomescape-backend-image.s3.ap-northeast-2.amazonaws.com/theme/0397f263-d9a8-4410-8f9f-a3023bc08bc4.jpg", "isWish": false, "isReview": false, "address": "전북 전주시 완산구 전주객사5길 30-2", "addressDetail": ""}, "comments": [], "likeCount": 0, "isLike": false, "reportCount": 0}, {"id": 262838, "themeId": 1589, "userId": 1463, "reviewLevel": 7, "userName": "종원사마", "playDate": "2021-03-16", "grade": 2.5, "level": "보통", "success": "성공", "extraTime": null, "remainingTime": null, "userHint": null, "content": ".", "isGrade": true, "createdAt": "03/16", "company": {"id": 79, "title": "마스터키 전주고사점", "isWish": false, "distance": 0, "createdAt": "2023-10-31"}, "theme": {"id": 1589, "companyName": "마스터키 전주고사점", "title": "인디아나 존스", "category": "추리", "time": 60, "thumbnail": "https://roomescape-backend-image.s3.ap-northeast-2.amazonaws.com/theme/0397f263-d9a8-4410-8f9f-a3023bc08bc4.jpg", "isWish": false, "isReview": false, "address": "전북 전주시 완산구 전주객사5길 30-2", "addressDetail": ""}, "comments": [], "likeCount": 0, "isLike": false, "reportCount": 0}, {"id": 241645, "themeId": 1589, "userId": 4267, "reviewLevel": 3, "userName": "뿌뿌뿌뿌", "playDate": "2021-02-11", "grade": 3, "level": "매우쉬움", "success": "성공", "extraTime": "26:00", "remainingTime": "34:00", "userHint": 0, "content": "쉽고 간단한 테마", "isGrade": true, "createdAt": "02/11", "company": {"id": 79, "title": "마스터키 전주고사점", "isWish": false, "distance": 0, "createdAt": "2023-10-31"}, "theme": {"id": 1589, "companyName": "마스터키 전주고사점", "title": "인디아나 존스", "category": "추리", "time": 60, "thumbnail": "https://roomescape-backend-image.s3.ap-northeast-2.amazonaws.com/theme/0397f263-d9a8-4410-8f9f-a3023bc08bc4.jpg", "isWish": false, "isReview": false, "address": "전북 전주시 완산구 전주객사5길 30-2", "addressDetail": ""}, "comments": [], "likeCount": 0, "isLike": false, "reportCount": 0}, {"id": 225840, "themeId": 1589, "userId": 5086, "reviewLevel": 5, "userName": "mooni", "playDate": "2021-01-16", "grade": 3, "level": "쉬움", "success": "성공", "extraTime": "30:00", "remainingTime": "30:00", "userHint": 1, "content": "재밋어요.", "isGrade": true, "createdAt": "01/16", "company": {"id": 79, "title": "마스터키 전주고사점", "isWish": false, "distance": 0, "createdAt": "2023-10-31"}, "theme": {"id": 1589, "companyName": "마스터키 전주고사점", "title": "인디아나 존스", "category": "추리", "time": 60, "thumbnail": "https://roomescape-backend-image.s3.ap-northeast-2.amazonaws.com/theme/0397f263-d9a8-4410-8f9f-a3023bc08bc4.jpg", "isWish": false, "isReview": false, "address": "전북 전주시 완산구 전주객사5길 30-2", "addressDetail": ""}, "comments": [], "likeCount": 0, "isLike": false, "reportCount": 0}, {"id": 224549, "themeId": 1589, "userId": 544, "reviewLevel": 6, "userName": "와이", "playDate": "2021-01-13", "grade": 1, "level": "쉬움", "success": "성공", "extraTime": "00:01", "remainingTime": "59:59", "userHint": 0, "content": "불친절", "isGrade": true, "createdAt": "01/13", "company": {"id": 79, "title": "마스터키 전주고사점", "isWish": false, "distance": 0, "createdAt": "2023-10-31"}, "theme": {"id": 1589, "companyName": "마스터키 전주고사점", "title": "인디아나 존스", "category": "추리", "time": 60, "thumbnail": "https://roomescape-backend-image.s3.ap-northeast-2.amazonaws.com/theme/0397f263-d9a8-4410-8f9f-a3023bc08bc4.jpg", "isWish": false, "isReview": false, "address": "전북 전주시 완산구 전주객사5길 30-2", "addressDetail": ""}, "comments": [], "likeCount": 0, "isLike": false, "reportCount": 0}, {"id": 320313, "themeId": 1589, "userId": 7265, "reviewLevel": 7, "userName": "쟁이", "playDate": "2021-01-12", "grade": 1.5, "level": "보통", "success": "성공", "extraTime": null, "remainingTime": null, "userHint": null, "content": ".", "isGrade": true, "createdAt": "01/12", "company": {"id": 79, "title": "마스터키 전주고사점", "isWish": false, "distance": 0, "createdAt": "2023-10-31"}, "theme": {"id": 1589, "companyName": "마스터키 전주고사점", "title": "인디아나 존스", "category": "추리", "time": 60, "thumbnail": "https://roomescape-backend-image.s3.ap-northeast-2.amazonaws.com/theme/0397f263-d9a8-4410-8f9f-a3023bc08bc4.jpg", "isWish": false, "isReview": false, "address": "전북 전주시 완산구 전주객사5길 30-2", "addressDetail": ""}, "comments": [], "likeCount": 0, "isLike": false, "reportCount": 0}, {"id": 223871, "themeId": 1589, "userId": 6032, "reviewLevel": 7, "userName": "빠야뽀야", "playDate": "2021-01-11", "grade": 3, "level": "쉬움", "success": "성공", "extraTime": null, "remainingTime": null, "userHint": null, "content": ".", "isGrade": true, "createdAt": "01/11", "company": {"id": 79, "title": "마스터키 전주고사점", "isWish": false, "distance": 0, "createdAt": "2023-10-31"}, "theme": {"id": 1589, "companyName": "마스터키 전주고사점", "title": "인디아나 존스", "category": "추리", "time": 60, "thumbnail": "https://roomescape-backend-image.s3.ap-northeast-2.amazonaws.com/theme/0397f263-d9a8-4410-8f9f-a3023bc08bc4.jpg", "isWish": false, "isReview": false, "address": "전북 전주시 완산구 전주객사5길 30-2", "addressDetail": ""}, "comments": [], "likeCount": 0, "isLike": false, "reportCount": 0}, {"id": 180242, "themeId": 1589, "userId": 4790, "reviewLevel": 3, "userName": "뫼비우스냥", "playDate": "2020-10-12", "grade": 2.5, "level": "보통", "success": "성공", "extraTime": null, "remainingTime": null, "userHint": null, "content": "2인 쉽고...", "isGrade": true, "createdAt": "10/12", "company": {"id": 79, "title": "마스터키 전주고사점", "isWish": false, "distance": 0, "createdAt": "2023-10-31"}, "theme": {"id": 1589, "companyName": "마스터키 전주고사점", "title": "인디아나 존스", "category": "추리", "time": 60, "thumbnail": "https://roomescape-backend-image.s3.ap-northeast-2.amazonaws.com/theme/0397f263-d9a8-4410-8f9f-a3023bc08bc4.jpg", "isWish": false, "isReview": false, "address": "전북 전주시 완산구 전주객사5길 30-2", "addressDetail": ""}, "comments": [], "likeCount": 0, "isLike": false, "reportCount": 0}, {"id": 161945, "themeId": 1589, "userId": 3497, "reviewLevel": 6, "userName": "JD", "playDate": "2020-09-11", "grade": 2.5, "level": "쉬움", "success": "성공", "extraTime": "37:00", "remainingTime": "23:00", "userHint": 0, "content": "감흥 없는 쉬운 문제, 평범한 인테리어 딱히 생각나는 것은 없지만 괜찮은 관찰력 문제가 하나 있었다", "isGrade": true, "createdAt": "09/11", "company": {"id": 79, "title": "마스터키 전주고사점", "isWish": false, "distance": 0, "createdAt": "2023-10-31"}, "theme": {"id": 1589, "companyName": "마스터키 전주고사점", "title": "인디아나 존스", "category": "추리", "time": 60, "thumbnail": "https://roomescape-backend-image.s3.ap-northeast-2.amazonaws.com/theme/0397f263-d9a8-4410-8f9f-a3023bc08bc4.jpg", "isWish": false, "isReview": false, "address": "전북 전주시 완산구 전주객사5길 30-2", "addressDetail": ""}, "comments": [], "likeCount": 0, "isLike": false, "reportCount": 0}, {"id": 161345, "themeId": 1589, "userId": 4619, "reviewLevel": 5, "userName": "우우웅", "playDate": "2020-09-11", "grade": 0, "level": "쉬움", "success": "성공", "extraTime": "37:00", "remainingTime": "23:00", "userHint": 0, "content": "2인", "isGrade": false, "createdAt": "09/11", "company": {"id": 79, "title": "마스터키 전주고사점", "isWish": false, "distance": 0, "createdAt": "2023-10-31"}, "theme": {"id": 1589, "companyName": "마스터키 전주고사점", "title": "인디아나 존스", "category": "추리", "time": 60, "thumbnail": "https://roomescape-backend-image.s3.ap-northeast-2.amazonaws.com/theme/0397f263-d9a8-4410-8f9f-a3023bc08bc4.jpg", "isWish": false, "isReview": false, "address": "전북 전주시 완산구 전주객사5길 30-2", "addressDetail": ""}, "comments": [], "likeCount": 0, "isLike": false, "reportCount": 0}, {"id": 142571, "themeId": 1589, "userId": 4205, "reviewLevel": 2, "userName": "방탈출잘하고싶다", "playDate": "2020-08-02", "grade": 3.5, "level": "쉬움", "success": "성공", "extraTime": null, "remainingTime": null, "userHint": null, "content": "#32", "isGrade": true, "createdAt": "08/02", "company": {"id": 79, "title": "마스터키 전주고사점", "isWish": false, "distance": 0, "createdAt": "2023-10-31"}, "theme": {"id": 1589, "companyName": "마스터키 전주고사점", "title": "인디아나 존스", "category": "추리", "time": 60, "thumbnail": "https://roomescape-backend-image.s3.ap-northeast-2.amazonaws.com/theme/0397f263-d9a8-4410-8f9f-a3023bc08bc4.jpg", "isWish": false, "isReview": false, "address": "전북 전주시 완산구 전주객사5길 30-2", "addressDetail": ""}, "comments": [], "likeCount": 0, "isLike": false, "reportCount": 0}, {"id": 138574, "themeId": 1589, "userId": 4085, "reviewLevel": 4, "userName": "HETO", "playDate": "2020-07-26", "grade": 0, "level": "쉬움", "success": "성공", "extraTime": "20:00", "remainingTime": "40:00", "userHint": 0, "content": "1", "isGrade": false, "createdAt": "07/26", "company": {"id": 79, "title": "마스터키 전주고사점", "isWish": false, "distance": 0, "createdAt": "2023-10-31"}, "theme": {"id": 1589, "companyName": "마스터키 전주고사점", "title": "인디아나 존스", "category": "추리", "time": 60, "thumbnail": "https://roomescape-backend-image.s3.ap-northeast-2.amazonaws.com/theme/0397f263-d9a8-4410-8f9f-a3023bc08bc4.jpg", "isWish": false, "isReview": false, "address": "전북 전주시 완산구 전주객사5길 30-2", "addressDetail": ""}, "comments": [], "likeCount": 0, "isLike": false, "reportCount": 0}, {"id": 283313, "themeId": 1589, "userId": 5291, "reviewLevel": 3, "userName": "치킨", "playDate": "2020-07-19", "grade": 4, "level": "쉬움", "success": "성공", "extraTime": "38:00", "remainingTime": "22:00", "userHint": 0, "content": "017. 이전방 모나리자가 아쉬워 쉬운방으로 힐링함. 중간 셋팅오류로 직원이 들어왔다 나갔지만 사소한 문제였음. 한 문제가 기억에 남는 테마. 재밌었다.", "isGrade": true, "createdAt": "07/19", "company": {"id": 79, "title": "마스터키 전주고사점", "isWish": false, "distance": 0, "createdAt": "2023-10-31"}, "theme": {"id": 1589, "companyName": "마스터키 전주고사점", "title": "인디아나 존스", "category": "추리", "time": 60, "thumbnail": "https://roomescape-backend-image.s3.ap-northeast-2.amazonaws.com/theme/0397f263-d9a8-4410-8f9f-a3023bc08bc4.jpg", "isWish": false, "isReview": false, "address": "전북 전주시 완산구 전주객사5길 30-2", "addressDetail": ""}, "comments": [], "likeCount": 0, "isLike": false, "reportCount": 0}, {"id": 133775, "themeId": 1589, "userId": 3923, "reviewLevel": 2, "userName": "혜마", "playDate": "2020-07-13", "grade": 3, "level": "보통", "success": "성공", "extraTime": "00:00", "remainingTime": "60:00", "userHint": null, "content": "20.06.07 2인", "isGrade": true, "createdAt": "07/13", "company": {"id": 79, "title": "마스터키 전주고사점", "isWish": false, "distance": 0, "createdAt": "2023-10-31"}, "theme": {"id": 1589, "companyName": "마스터키 전주고사점", "title": "인디아나 존스", "category": "추리", "time": 60, "thumbnail": "https://roomescape-backend-image.s3.ap-northeast-2.amazonaws.com/theme/0397f263-d9a8-4410-8f9f-a3023bc08bc4.jpg", "isWish": false, "isReview": false, "address": "전북 전주시 완산구 전주객사5길 30-2", "addressDetail": ""}, "comments": [], "likeCount": 0, "isLike": false, "reportCount": 0}, {"id": 128106, "themeId": 1589, "userId": 139, "reviewLevel": 7, "userName": "신정", "playDate": "2020-07-03", "grade": 2.5, "level": "보통", "success": "성공", "extraTime": "23:00", "remainingTime": "37:00", "userHint": 0, "content": "2017.11.12/2인", "isGrade": true, "createdAt": "07/03", "company": {"id": 79, "title": "마스터키 전주고사점", "isWish": false, "distance": 0, "createdAt": "2023-10-31"}, "theme": {"id": 1589, "companyName": "마스터키 전주고사점", "title": "인디아나 존스", "category": "추리", "time": 60, "thumbnail": "https://roomescape-backend-image.s3.ap-northeast-2.amazonaws.com/theme/0397f263-d9a8-4410-8f9f-a3023bc08bc4.jpg", "isWish": false, "isReview": false, "address": "전북 전주시 완산구 전주객사5길 30-2", "addressDetail": ""}, "comments": [], "likeCount": 0, "isLike": false, "reportCount": 0}, {"id": 97633, "themeId": 1589, "userId": 637, "reviewLevel": 4, "userName": "01000", "playDate": "2020-05-11", "grade": 3, "level": "쉬움", "success": "성공", "extraTime": "35:00", "remainingTime": "25:00", "userHint": 0, "content": "쉽다 전방 난이도 내립시다", "isGrade": true, "createdAt": "05/11", "company": {"id": 79, "title": "마스터키 전주고사점", "isWish": false, "distance": 0, "createdAt": "2023-10-31"}, "theme": {"id": 1589, "companyName": "마스터키 전주고사점", "title": "인디아나 존스", "category": "추리", "time": 60, "thumbnail": "https://roomescape-backend-image.s3.ap-northeast-2.amazonaws.com/theme/0397f263-d9a8-4410-8f9f-a3023bc08bc4.jpg", "isWish": false, "isReview": false, "address": "전북 전주시 완산구 전주객사5길 30-2", "addressDetail": ""}, "comments": [], "likeCount": 0, "isLike": false, "reportCount": 0}, {"id": 93745, "themeId": 1589, "userId": 2967, "reviewLevel": 1, "userName": "해가떠버렸다", "playDate": "2020-05-04", "grade": 3, "level": "쉬움", "success": "성공", "extraTime": "30:43", "remainingTime": "29:17", "userHint": 0, "content": "No.13 2인", "isGrade": true, "createdAt": "05/04", "company": {"id": 79, "title": "마스터키 전주고사점", "isWish": false, "distance": 0, "createdAt": "2023-10-31"}, "theme": {"id": 1589, "companyName": "마스터키 전주고사점", "title": "인디아나 존스", "category": "추리", "time": 60, "thumbnail": "https://roomescape-backend-image.s3.ap-northeast-2.amazonaws.com/theme/0397f263-d9a8-4410-8f9f-a3023bc08bc4.jpg", "isWish": false, "isReview": false, "address": "전북 전주시 완산구 전주객사5길 30-2", "addressDetail": ""}, "comments": [], "likeCount": 0, "isLike": false, "reportCount": 0}, {"id": 90739, "themeId": 1589, "userId": 225, "reviewLevel": 5, "userName": "바스켓카운트", "playDate": "2020-01-07", "grade": 3, "level": "쉬움", "success": "성공", "extraTime": "30:00", "remainingTime": "30:00", "userHint": 0, "content": "#179#4인", "isGrade": true, "createdAt": "01/07", "company": {"id": 79, "title": "마스터키 전주고사점", "isWish": false, "distance": 0, "createdAt": "2023-10-31"}, "theme": {"id": 1589, "companyName": "마스터키 전주고사점", "title": "인디아나 존스", "category": "추리", "time": 60, "thumbnail": "https://roomescape-backend-image.s3.ap-northeast-2.amazonaws.com/theme/0397f263-d9a8-4410-8f9f-a3023bc08bc4.jpg", "isWish": false, "isReview": false, "address": "전북 전주시 완산구 전주객사5길 30-2", "addressDetail": ""}, "comments": [], "likeCount": 0, "isLike": false, "reportCount": 0}, {"id": 32026, "themeId": 1589, "userId": 565, "reviewLevel": 6, "userName": "탈출함니다", "playDate": "2019-11-20", "grade": 4, "level": "쉬움", "success": "성공", "extraTime": "25:00", "remainingTime": "35:00", "userHint": 0, "content": "중간에 한문제에서 엄청 애먹었고 문제를 이런식으로 구성할 수도 있겠구나 하고 배워갑니다.. !!! 무난무난하게 엄청쉽고 재밌어요 !!", "isGrade": true, "createdAt": "11/20", "company": {"id": 79, "title": "마스터키 전주고사점", "isWish": false, "distance": 0, "createdAt": "2023-10-31"}, "theme": {"id": 1589, "companyName": "마스터키 전주고사점", "title": "인디아나 존스", "category": "추리", "time": 60, "thumbnail": "https://roomescape-backend-image.s3.ap-northeast-2.amazonaws.com/theme/0397f263-d9a8-4410-8f9f-a3023bc08bc4.jpg", "isWish": false, "isReview": false, "address": "전북 전주시 완산구 전주객사5길 30-2", "addressDetail": ""}, "comments": [], "likeCount": 0, "isLike": false, "reportCount": 0}, {"id": 479818, "themeId": 1589, "userId": 46, "reviewLevel": 8, "userName": "LaserBeam", "playDate": "2019-11-09", "grade": 0, "level": "쉬움", "success": "성공", "extraTime": "45:00", "remainingTime": "15:00", "userHint": 0, "content": "옵", "isGrade": false, "createdAt": "11/09", "company": {"id": 79, "title": "마스터키 전주고사점", "isWish": false, "distance": 0, "createdAt": "2023-10-31"}, "theme": {"id": 1589, "companyName": "마스터키 전주고사점", "title": "인디아나 존스", "category": "추리", "time": 60, "thumbnail": "https://roomescape-backend-image.s3.ap-northeast-2.amazonaws.com/theme/0397f263-d9a8-4410-8f9f-a3023bc08bc4.jpg", "isWish": false, "isReview": false, "address": "전북 전주시 완산구 전주객사5길 30-2", "addressDetail": ""}, "comments": [], "likeCount": 0, "isLike": false, "reportCount": 0}, {"id": 28731, "themeId": 1589, "userId": 929, "reviewLevel": 8, "userName": "Salux", "playDate": "2019-11-09", "grade": 3, "level": "쉬움", "success": "성공", "extraTime": "45:00", "remainingTime": "15:00", "userHint": 0, "content": "옵저버 끼고 혼방플레이 쉬운데 잘 만들었다", "isGrade": true, "createdAt": "11/09", "company": {"id": 79, "title": "마스터키 전주고사점", "isWish": false, "distance": 0, "createdAt": "2023-10-31"}, "theme": {"id": 1589, "companyName": "마스터키 전주고사점", "title": "인디아나 존스", "category": "추리", "time": 60, "thumbnail": "https://roomescape-backend-image.s3.ap-northeast-2.amazonaws.com/theme/0397f263-d9a8-4410-8f9f-a3023bc08bc4.jpg", "isWish": false, "isReview": false, "address": "전북 전주시 완산구 전주객사5길 30-2", "addressDetail": ""}, "comments": [], "likeCount": 0, "isLike": false, "reportCount": 0}, {"id": 4622, "themeId": 1589, "userId": 542, "reviewLevel": 8, "userName": "쿤", "playDate": "2019-08-10", "grade": 0, "level": "보통", "success": "성공", "extraTime": "34:25", "remainingTime": "25:35", "userHint": 0, "content": "재밌었습니다 ㅎㅎ", "isGrade": false, "createdAt": "08/10", "company": {"id": 79, "title": "마스터키 전주고사점", "isWish": false, "distance": 0, "createdAt": "2023-10-31"}, "theme": {"id": 1589, "companyName": "마스터키 전주고사점", "title": "인디아나 존스", "category": "추리", "time": 60, "thumbnail": "https://roomescape-backend-image.s3.ap-northeast-2.amazonaws.com/theme/0397f263-d9a8-4410-8f9f-a3023bc08bc4.jpg", "isWish": false, "isReview": false, "address": "전북 전주시 완산구 전주객사5길 30-2", "addressDetail": ""}, "comments": [], "likeCount": 0, "isLike": false, "reportCount": 0}, {"id": 2785, "themeId": 1589, "userId": 562, "reviewLevel": 7, "userName": "신다", "playDate": "2019-07-31", "grade": 3.5, "level": "쉬움", "success": "성공", "extraTime": "23:00", "remainingTime": "37:00", "userHint": 0, "content": ".", "isGrade": true, "createdAt": "07/31", "company": {"id": 79, "title": "마스터키 전주고사점", "isWish": false, "distance": 0, "createdAt": "2023-10-31"}, "theme": {"id": 1589, "companyName": "마스터키 전주고사점", "title": "인디아나 존스", "category": "추리", "time": 60, "thumbnail": "https://roomescape-backend-image.s3.ap-northeast-2.amazonaws.com/theme/0397f263-d9a8-4410-8f9f-a3023bc08bc4.jpg", "isWish": false, "isReview": false, "address": "전북 전주시 완산구 전주객사5길 30-2", "addressDetail": ""}, "comments": [], "likeCount": 0, "isLike": false, "reportCount": 0}, {"id": 21331, "themeId": 1589, "userId": 56, "reviewLevel": 8, "userName": "과자", "playDate": "2018-02-10", "grade": 2.5, "level": "보통", "success": "성공", "extraTime": "34:25", "remainingTime": "25:35", "userHint": 0, "content": "161.컨셉 자체가 취향에 맞아서 재밌게 했던 테마. 전체적으로는 무난한편. 20180210", "isGrade": true, "createdAt": "02/10", "company": {"id": 79, "title": "마스터키 전주고사점", "isWish": false, "distance": 0, "createdAt": "2023-10-31"}, "theme": {"id": 1589, "companyName": "마스터키 전주고사점", "title": "인디아나 존스", "category": "추리", "time": 60, "thumbnail": "https://roomescape-backend-image.s3.ap-northeast-2.amazonaws.com/theme/0397f263-d9a8-4410-8f9f-a3023bc08bc4.jpg", "isWish": false, "isReview": false, "address": "전북 전주시 완산구 전주객사5길 30-2", "addressDetail": ""}, "comments": [], "likeCount": 0, "isLike": false, "reportCount": 0}]}