{"id": 3014, "companyId": 637, "companyName": "코드나인 방탈출카페", "companyTel": "041-357-1313", "companyHomepage": "https://naver.me/GLKORuz0", "title": "도둑들-문제도둑", "intro": "몽블랑 미술관에 괴도 루팡으로부터 모든 미술품을 훔치겠다는 초대장이 날아왔다. 며칠 뒤 마법을 부린 듯 괴도루팡은 미술품들을 하나씩 훔쳐가고 (본 테마는 도둑들 테마의 문제 리뉴얼 버전 입니다)", "category": "잠입", "typeOnly": false, "typeDifferent": false, "typeNew": false, "level": 4, "recommendPerson": 2, "tool": "보통", "activity": "낮음", "time": 60, "grade": 3.4, "thumbnail": "https://roomescape-backend-image.s3.ap-northeast-2.amazonaws.com/theme/b592a01d-3ed1-41bd-aaf7-124c4c6fcc4b.jpg", "reviewCount": 11, "wishCount": 6, "isWish": false, "images": [], "themePrices": [], "isReview": false, "address": "충남 당진시 당진중앙2로 85-6", "addressDetail": "2층", "active": true, "main": false, "sortCode": 0, "review_list": [{"id": 583354, "themeId": 3014, "userId": 632, "reviewLevel": 8, "userName": "레콤", "playDate": "2021-02-04", "grade": 0, "level": "쉬움", "success": "성공", "extraTime": "42:58", "remainingTime": "17:02", "userHint": 0, "content": " ", "isGrade": false, "createdAt": "09/22", "company": {"id": 637, "title": "코드나인 방탈출카페", "isWish": false, "distance": 0, "createdAt": "2023-10-31"}, "theme": {"id": 3014, "companyName": "코드나인 방탈출카페", "title": "도둑들-문제도둑", "category": "잠입", "time": 60, "thumbnail": "https://roomescape-backend-image.s3.ap-northeast-2.amazonaws.com/theme/b592a01d-3ed1-41bd-aaf7-124c4c6fcc4b.jpg", "isWish": false, "isReview": false, "address": "충남 당진시 당진중앙2로 85-6", "addressDetail": "2층"}, "comments": [], "likeCount": 0, "isLike": false, "reportCount": 0}, {"id": 547706, "themeId": 3014, "userId": 14370, "reviewLevel": 1, "userName": "토로레", "playDate": "2022-06-11", "grade": 3, "level": "보통", "success": "성공", "extraTime": "14:58", "remainingTime": "45:02", "userHint": 2, "content": "장치노후화가 심함ㅜㅜ\n\n", "isGrade": true, "createdAt": "07/27", "company": {"id": 637, "title": "코드나인 방탈출카페", "isWish": false, "distance": 0, "createdAt": "2023-10-31"}, "theme": {"id": 3014, "companyName": "코드나인 방탈출카페", "title": "도둑들-문제도둑", "category": "잠입", "time": 60, "thumbnail": "https://roomescape-backend-image.s3.ap-northeast-2.amazonaws.com/theme/b592a01d-3ed1-41bd-aaf7-124c4c6fcc4b.jpg", "isWish": false, "isReview": false, "address": "충남 당진시 당진중앙2로 85-6", "addressDetail": "2층"}, "comments": [], "likeCount": 0, "isLike": false, "reportCount": 0}, {"id": 540201, "themeId": 3014, "userId": 7587, "reviewLevel": 8, "userName": "강남방린이", "playDate": "2022-07-18", "grade": 3.5, "level": "쉬움", "success": "성공", "extraTime": "25:25", "remainingTime": "34:35", "userHint": 0, "content": "4인", "isGrade": true, "createdAt": "07/18", "company": {"id": 637, "title": "코드나인 방탈출카페", "isWish": false, "distance": 0, "createdAt": "2023-10-31"}, "theme": {"id": 3014, "companyName": "코드나인 방탈출카페", "title": "도둑들-문제도둑", "category": "잠입", "time": 60, "thumbnail": "https://roomescape-backend-image.s3.ap-northeast-2.amazonaws.com/theme/b592a01d-3ed1-41bd-aaf7-124c4c6fcc4b.jpg", "isWish": false, "isReview": false, "address": "충남 당진시 당진중앙2로 85-6", "addressDetail": "2층"}, "comments": [], "likeCount": 0, "isLike": false, "reportCount": 0}, {"id": 510903, "themeId": 3014, "userId": 11028, "reviewLevel": 1, "userName": "ROSY", "playDate": "2022-05-30", "grade": 4.5, "level": "어려움", "success": "실패", "extraTime": null, "remainingTime": null, "userHint": null, "content": "방린이한텐 어렵지만 어려워서 재밌다", "isGrade": true, "createdAt": "05/30", "company": {"id": 637, "title": "코드나인 방탈출카페", "isWish": false, "distance": 0, "createdAt": "2023-10-31"}, "theme": {"id": 3014, "companyName": "코드나인 방탈출카페", "title": "도둑들-문제도둑", "category": "잠입", "time": 60, "thumbnail": "https://roomescape-backend-image.s3.ap-northeast-2.amazonaws.com/theme/b592a01d-3ed1-41bd-aaf7-124c4c6fcc4b.jpg", "isWish": false, "isReview": false, "address": "충남 당진시 당진중앙2로 85-6", "addressDetail": "2층"}, "comments": [], "likeCount": 0, "isLike": false, "reportCount": 0}, {"id": 370837, "themeId": 3014, "userId": 7603, "reviewLevel": 6, "userName": "야방", "playDate": "2021-09-20", "grade": 3, "level": "보통", "success": "성공", "extraTime": "25:25", "remainingTime": "34:35", "userHint": 0, "content": "4인", "isGrade": true, "createdAt": "09/20", "company": {"id": 637, "title": "코드나인 방탈출카페", "isWish": false, "distance": 0, "createdAt": "2023-10-31"}, "theme": {"id": 3014, "companyName": "코드나인 방탈출카페", "title": "도둑들-문제도둑", "category": "잠입", "time": 60, "thumbnail": "https://roomescape-backend-image.s3.ap-northeast-2.amazonaws.com/theme/b592a01d-3ed1-41bd-aaf7-124c4c6fcc4b.jpg", "isWish": false, "isReview": false, "address": "충남 당진시 당진중앙2로 85-6", "addressDetail": "2층"}, "comments": [], "likeCount": 0, "isLike": false, "reportCount": 0}, {"id": 312487, "themeId": 3014, "userId": 3916, "reviewLevel": 3, "userName": "율광", "playDate": "2021-06-11", "grade": 3, "level": "보통", "success": "성공", "extraTime": "14:06", "remainingTime": "45:54", "userHint": null, "content": "쏘쏘", "isGrade": true, "createdAt": "06/11", "company": {"id": 637, "title": "코드나인 방탈출카페", "isWish": false, "distance": 0, "createdAt": "2023-10-31"}, "theme": {"id": 3014, "companyName": "코드나인 방탈출카페", "title": "도둑들-문제도둑", "category": "잠입", "time": 60, "thumbnail": "https://roomescape-backend-image.s3.ap-northeast-2.amazonaws.com/theme/b592a01d-3ed1-41bd-aaf7-124c4c6fcc4b.jpg", "isWish": false, "isReview": false, "address": "충남 당진시 당진중앙2로 85-6", "addressDetail": "2층"}, "comments": [], "likeCount": 0, "isLike": false, "reportCount": 0}, {"id": 310430, "themeId": 3014, "userId": 8053, "reviewLevel": 2, "userName": "bongbong", "playDate": "2021-06-09", "grade": 5, "level": "어려움", "success": "성공", "extraTime": null, "remainingTime": null, "userHint": null, "content": "억지 문제 좀..?", "isGrade": true, "createdAt": "06/09", "company": {"id": 637, "title": "코드나인 방탈출카페", "isWish": false, "distance": 0, "createdAt": "2023-10-31"}, "theme": {"id": 3014, "companyName": "코드나인 방탈출카페", "title": "도둑들-문제도둑", "category": "잠입", "time": 60, "thumbnail": "https://roomescape-backend-image.s3.ap-northeast-2.amazonaws.com/theme/b592a01d-3ed1-41bd-aaf7-124c4c6fcc4b.jpg", "isWish": false, "isReview": false, "address": "충남 당진시 당진중앙2로 85-6", "addressDetail": "2층"}, "comments": [], "likeCount": 0, "isLike": false, "reportCount": 0}, {"id": 294389, "themeId": 3014, "userId": 7848, "reviewLevel": 1, "userName": "우동동", "playDate": "2021-05-12", "grade": 3.5, "level": "보통", "success": "성공", "extraTime": null, "remainingTime": null, "userHint": null, "content": "3인", "isGrade": true, "createdAt": "05/12", "company": {"id": 637, "title": "코드나인 방탈출카페", "isWish": false, "distance": 0, "createdAt": "2023-10-31"}, "theme": {"id": 3014, "companyName": "코드나인 방탈출카페", "title": "도둑들-문제도둑", "category": "잠입", "time": 60, "thumbnail": "https://roomescape-backend-image.s3.ap-northeast-2.amazonaws.com/theme/b592a01d-3ed1-41bd-aaf7-124c4c6fcc4b.jpg", "isWish": false, "isReview": false, "address": "충남 당진시 당진중앙2로 85-6", "addressDetail": "2층"}, "comments": [], "likeCount": 0, "isLike": false, "reportCount": 0}, {"id": 281807, "themeId": 3014, "userId": 7459, "reviewLevel": 2, "userName": "응스응", "playDate": "2021-04-18", "grade": 2.5, "level": "보통", "success": "성공", "extraTime": "00:00", "remainingTime": "60:00", "userHint": null, "content": "쏘쏘", "isGrade": true, "createdAt": "04/18", "company": {"id": 637, "title": "코드나인 방탈출카페", "isWish": false, "distance": 0, "createdAt": "2023-10-31"}, "theme": {"id": 3014, "companyName": "코드나인 방탈출카페", "title": "도둑들-문제도둑", "category": "잠입", "time": 60, "thumbnail": "https://roomescape-backend-image.s3.ap-northeast-2.amazonaws.com/theme/b592a01d-3ed1-41bd-aaf7-124c4c6fcc4b.jpg", "isWish": false, "isReview": false, "address": "충남 당진시 당진중앙2로 85-6", "addressDetail": "2층"}, "comments": [], "likeCount": 0, "isLike": false, "reportCount": 0}, {"id": 324815, "themeId": 3014, "userId": 7265, "reviewLevel": 7, "userName": "쟁이", "playDate": "2021-01-26", "grade": 3, "level": "보통", "success": "성공", "extraTime": null, "remainingTime": null, "userHint": null, "content": ".", "isGrade": true, "createdAt": "01/26", "company": {"id": 637, "title": "코드나인 방탈출카페", "isWish": false, "distance": 0, "createdAt": "2023-10-31"}, "theme": {"id": 3014, "companyName": "코드나인 방탈출카페", "title": "도둑들-문제도둑", "category": "잠입", "time": 60, "thumbnail": "https://roomescape-backend-image.s3.ap-northeast-2.amazonaws.com/theme/b592a01d-3ed1-41bd-aaf7-124c4c6fcc4b.jpg", "isWish": false, "isReview": false, "address": "충남 당진시 당진중앙2로 85-6", "addressDetail": "2층"}, "comments": [], "likeCount": 0, "isLike": false, "reportCount": 0}, {"id": 184405, "themeId": 3014, "userId": 4619, "reviewLevel": 5, "userName": "우우웅", "playDate": "2020-10-22", "grade": 0, "level": "쉬움", "success": "성공", "extraTime": "01:00", "remainingTime": "59:00", "userHint": 2, "content": "2인", "isGrade": false, "createdAt": "10/22", "company": {"id": 637, "title": "코드나인 방탈출카페", "isWish": false, "distance": 0, "createdAt": "2023-10-31"}, "theme": {"id": 3014, "companyName": "코드나인 방탈출카페", "title": "도둑들-문제도둑", "category": "잠입", "time": 60, "thumbnail": "https://roomescape-backend-image.s3.ap-northeast-2.amazonaws.com/theme/b592a01d-3ed1-41bd-aaf7-124c4c6fcc4b.jpg", "isWish": false, "isReview": false, "address": "충남 당진시 당진중앙2로 85-6", "addressDetail": "2층"}, "comments": [], "likeCount": 0, "isLike": false, "reportCount": 0}]}