{"id": 3069, "companyId": 644, "companyName": "룸즈에이 포항점", "companyTel": "054-247-4147", "companyHomepage": "http://roomsa.co.kr/sub/sub04.asp?R_JIJEM=S11", "title": "안개꽃", "intro": "화가인 그가 내게서 떠나간지 어느덧 한 달, 나는 여전히 그와의 시간 속에 머물러 있다. 그리움과 원망을 가득 안고 골목길을 걷던 어느 날, 밤공기를 들이마시며 한 걸음씩 내딛던 나는 작은 골목길과는 어울리지 않는 전시관을 보게 되었다. 처음 보는 전시관이었지만 어디선가 그의 향기가 흘러나오는 듯 했고, 그 추억 속의 향기에 이끌려 전시회장 안으로 들어서게 되었다.", "category": "드라마", "typeOnly": false, "typeDifferent": false, "typeNew": false, "level": 3, "recommendPerson": 2, "tool": "보통", "activity": "낮음", "time": 60, "grade": 3.1, "thumbnail": "https://roomescape-backend-image.s3.ap-northeast-2.amazonaws.com/theme/c2c7d014-b552-4879-9c9d-540abac5f74c.jpg", "reviewCount": 24, "wishCount": 6, "isWish": false, "images": [], "themePrices": [], "isReview": false, "address": "경북 포항시 북구 중앙로 273", "addressDetail": "5층", "active": true, "main": false, "sortCode": 0, "review_list": [{"id": 839001, "themeId": 3069, "userId": 47213, "reviewLevel": 2, "userName": "째롱", "playDate": "2023-10-21", "grade": 0, "level": "쉬움", "success": "성공", "extraTime": null, "remainingTime": null, "userHint": null, "content": "퀄이 별로임", "isGrade": false, "createdAt": "10/22", "company": {"id": 644, "title": "룸즈에이 포항점", "isWish": false, "distance": 0, "createdAt": "2023-10-31"}, "theme": {"id": 3069, "companyName": "룸즈에이 포항점", "title": "안개꽃", "category": "드라마", "time": 60, "thumbnail": "https://roomescape-backend-image.s3.ap-northeast-2.amazonaws.com/theme/c2c7d014-b552-4879-9c9d-540abac5f74c.jpg", "isWish": false, "isReview": false, "address": "경북 포항시 북구 중앙로 273", "addressDetail": "5층"}, "comments": [], "likeCount": 0, "isLike": false, "reportCount": 0}, {"id": 814841, "themeId": 3069, "userId": 6653, "reviewLevel": 5, "userName": "호두파이", "playDate": "2023-09-02", "grade": 3, "level": "보통", "success": "성공", "extraTime": "15:52", "remainingTime": "44:08", "userHint": 0, "content": "#223\n2인. 문제 자체는 어렵지 않지만 가이드가 어질어질하다. 스토리는 좋았다. 나름 장치들이 많이 있지만 볼륨이 적은 느낌이라 아쉬운점도 있다.", "isGrade": true, "createdAt": "09/15", "company": {"id": 644, "title": "룸즈에이 포항점", "isWish": false, "distance": 0, "createdAt": "2023-10-31"}, "theme": {"id": 3069, "companyName": "룸즈에이 포항점", "title": "안개꽃", "category": "드라마", "time": 60, "thumbnail": "https://roomescape-backend-image.s3.ap-northeast-2.amazonaws.com/theme/c2c7d014-b552-4879-9c9d-540abac5f74c.jpg", "isWish": false, "isReview": false, "address": "경북 포항시 북구 중앙로 273", "addressDetail": "5층"}, "comments": [], "likeCount": 0, "isLike": false, "reportCount": 0}, {"id": 751428, "themeId": 3069, "userId": 36885, "reviewLevel": 2, "userName": "쎄양양", "playDate": "2023-05-28", "grade": 3.5, "level": "쉬움", "success": "성공", "extraTime": "22:00", "remainingTime": "38:00", "userHint": 3, "content": "#42 (2인)", "isGrade": true, "createdAt": "06/12", "company": {"id": 644, "title": "룸즈에이 포항점", "isWish": false, "distance": 0, "createdAt": "2023-10-31"}, "theme": {"id": 3069, "companyName": "룸즈에이 포항점", "title": "안개꽃", "category": "드라마", "time": 60, "thumbnail": "https://roomescape-backend-image.s3.ap-northeast-2.amazonaws.com/theme/c2c7d014-b552-4879-9c9d-540abac5f74c.jpg", "isWish": false, "isReview": false, "address": "경북 포항시 북구 중앙로 273", "addressDetail": "5층"}, "comments": [], "likeCount": 0, "isLike": false, "reportCount": 0}, {"id": 683812, "themeId": 3069, "userId": 5967, "reviewLevel": 4, "userName": "오늘하루도푸름", "playDate": "2023-02-28", "grade": 5, "level": "쉬움", "success": "성공", "extraTime": null, "remainingTime": null, "userHint": null, "content": ".", "isGrade": true, "createdAt": "02/28", "company": {"id": 644, "title": "룸즈에이 포항점", "isWish": false, "distance": 0, "createdAt": "2023-10-31"}, "theme": {"id": 3069, "companyName": "룸즈에이 포항점", "title": "안개꽃", "category": "드라마", "time": 60, "thumbnail": "https://roomescape-backend-image.s3.ap-northeast-2.amazonaws.com/theme/c2c7d014-b552-4879-9c9d-540abac5f74c.jpg", "isWish": false, "isReview": false, "address": "경북 포항시 북구 중앙로 273", "addressDetail": "5층"}, "comments": [], "likeCount": 0, "isLike": false, "reportCount": 0}, {"id": 663844, "themeId": 3069, "userId": 29499, "reviewLevel": 2, "userName": "dyuum", "playDate": "2023-01-26", "grade": 5, "level": "보통", "success": "성공", "extraTime": null, "remainingTime": null, "userHint": 5, "content": "탈출했지만 힌트 5개 사용해서 실패!(3개까지 성공 인정)\n커플에게 추천하는 테마입니다. 몰입하게 돼요.\n문제도 신기해서 재밌었어용!", "isGrade": true, "createdAt": "01/26", "company": {"id": 644, "title": "룸즈에이 포항점", "isWish": false, "distance": 0, "createdAt": "2023-10-31"}, "theme": {"id": 3069, "companyName": "룸즈에이 포항점", "title": "안개꽃", "category": "드라마", "time": 60, "thumbnail": "https://roomescape-backend-image.s3.ap-northeast-2.amazonaws.com/theme/c2c7d014-b552-4879-9c9d-540abac5f74c.jpg", "isWish": false, "isReview": false, "address": "경북 포항시 북구 중앙로 273", "addressDetail": "5층"}, "comments": [], "likeCount": 0, "isLike": false, "reportCount": 0}, {"id": 627455, "themeId": 3069, "userId": 29660, "reviewLevel": 1, "userName": "Horus", "playDate": "2022-11-05", "grade": 3.5, "level": "보통", "success": "실패", "extraTime": null, "remainingTime": null, "userHint": 3, "content": ".", "isGrade": true, "createdAt": "11/29", "company": {"id": 644, "title": "룸즈에이 포항점", "isWish": false, "distance": 0, "createdAt": "2023-10-31"}, "theme": {"id": 3069, "companyName": "룸즈에이 포항점", "title": "안개꽃", "category": "드라마", "time": 60, "thumbnail": "https://roomescape-backend-image.s3.ap-northeast-2.amazonaws.com/theme/c2c7d014-b552-4879-9c9d-540abac5f74c.jpg", "isWish": false, "isReview": false, "address": "경북 포항시 북구 중앙로 273", "addressDetail": "5층"}, "comments": [], "likeCount": 0, "isLike": false, "reportCount": 0}, {"id": 588566, "themeId": 3069, "userId": 13964, "reviewLevel": 3, "userName": "해충박멸회사직원", "playDate": "2022-09-29", "grade": 3, "level": "보통", "success": "성공", "extraTime": "06:15", "remainingTime": "53:45", "userHint": 1, "content": "47방\n열받는 장치 인식+초어거지 문제+TTS 내레이션\n그나마 진행 방식이 맘에 들어서 다행\n전국에 복붙할거면 전문 성우를 쓰는게 맞지 않을까 싶다", "isGrade": true, "createdAt": "09/29", "company": {"id": 644, "title": "룸즈에이 포항점", "isWish": false, "distance": 0, "createdAt": "2023-10-31"}, "theme": {"id": 3069, "companyName": "룸즈에이 포항점", "title": "안개꽃", "category": "드라마", "time": 60, "thumbnail": "https://roomescape-backend-image.s3.ap-northeast-2.amazonaws.com/theme/c2c7d014-b552-4879-9c9d-540abac5f74c.jpg", "isWish": false, "isReview": false, "address": "경북 포항시 북구 중앙로 273", "addressDetail": "5층"}, "comments": [], "likeCount": 0, "isLike": false, "reportCount": 0}, {"id": 482062, "themeId": 3069, "userId": 11908, "reviewLevel": 4, "userName": "꾸마", "playDate": "2022-04-05", "grade": 2, "level": "보통", "success": "실패", "extraTime": null, "remainingTime": null, "userHint": 4, "content": "완전 방린이 때 갔던 방탈출! 끈기 없는 사람이 가면 턱 막히는 구간 있음..ㅎㅎ 인테리어 좋았구 깔끔 했다! 어려운 문제는 딱히 없었구 제가 갔을때는 장치 오류 없었음! 기승전결이 있는 테마라서 스토리 면은 좋았다", "isGrade": true, "createdAt": "04/05", "company": {"id": 644, "title": "룸즈에이 포항점", "isWish": false, "distance": 0, "createdAt": "2023-10-31"}, "theme": {"id": 3069, "companyName": "룸즈에이 포항점", "title": "안개꽃", "category": "드라마", "time": 60, "thumbnail": "https://roomescape-backend-image.s3.ap-northeast-2.amazonaws.com/theme/c2c7d014-b552-4879-9c9d-540abac5f74c.jpg", "isWish": false, "isReview": false, "address": "경북 포항시 북구 중앙로 273", "addressDetail": "5층"}, "comments": [], "likeCount": 0, "isLike": false, "reportCount": 0}, {"id": 477555, "themeId": 3069, "userId": 7366, "reviewLevel": 3, "userName": "케미man", "playDate": "2022-03-27", "grade": 2, "level": "어려움", "success": "성공", "extraTime": null, "remainingTime": null, "userHint": null, "content": "룸즈에이는 가끔 이런 테마가 존재하는데 장르에 충실하다고 밖에 할 말이 없음 처음 하는 사람에게는 비추 하지만 참신한 건 인정", "isGrade": true, "createdAt": "03/27", "company": {"id": 644, "title": "룸즈에이 포항점", "isWish": false, "distance": 0, "createdAt": "2023-10-31"}, "theme": {"id": 3069, "companyName": "룸즈에이 포항점", "title": "안개꽃", "category": "드라마", "time": 60, "thumbnail": "https://roomescape-backend-image.s3.ap-northeast-2.amazonaws.com/theme/c2c7d014-b552-4879-9c9d-540abac5f74c.jpg", "isWish": false, "isReview": false, "address": "경북 포항시 북구 중앙로 273", "addressDetail": "5층"}, "comments": [], "likeCount": 0, "isLike": false, "reportCount": 0}, {"id": 436815, "themeId": 3069, "userId": 5364, "reviewLevel": 3, "userName": "안타고", "playDate": "2022-01-16", "grade": 1.5, "level": "어려움", "success": "실패", "extraTime": "01:21", "remainingTime": "58:39", "userHint": 4, "content": "포항 룸즈에이 연방 2인 (힌트 갯수 초과로 실패) 항상 느끼는거지만 룸즈에이는 장치와의 교감이 매.우.매.우. 중요하다. 테마 내 문제의 절반이 장치였는데 먹히질 않아 플레이 흐름과 집중도가 굉장히 많이 떨어졌다. (힌트갯수가 많은거도 정답이 하나밖에 없는데 먹히질 않아 확인겸했던 것들이다.) 테마 후반에는 빨리 나가고싶다는 생각밖에.. 감성테마인데 장치오류들로 이렇게밖에 느끼지 못한게 굉장히 아쉽다.(테마 난이도가 어려움인 이유는 장치교감이 안될 경우 굉장히 어렵게 될 수 있기 때문.) 장치, 감성테마 좋아하시는 분 추천.", "isGrade": true, "createdAt": "01/16", "company": {"id": 644, "title": "룸즈에이 포항점", "isWish": false, "distance": 0, "createdAt": "2023-10-31"}, "theme": {"id": 3069, "companyName": "룸즈에이 포항점", "title": "안개꽃", "category": "드라마", "time": 60, "thumbnail": "https://roomescape-backend-image.s3.ap-northeast-2.amazonaws.com/theme/c2c7d014-b552-4879-9c9d-540abac5f74c.jpg", "isWish": false, "isReview": false, "address": "경북 포항시 북구 중앙로 273", "addressDetail": "5층"}, "comments": [], "likeCount": 0, "isLike": false, "reportCount": 0}, {"id": 421191, "themeId": 3069, "userId": 10501, "reviewLevel": 4, "userName": "메테오", "playDate": "2021-12-26", "grade": 3, "level": "보통", "success": "성공", "extraTime": "02:00", "remainingTime": "58:00", "userHint": 2, "content": "인테리어가 너무 이쁨 장치오류 2개..... 테마는 재밌는데 장치 오류 너무 아쉽 ㅠㅠ 그래도 재밌당 ㅎㅎ", "isGrade": true, "createdAt": "12/26", "company": {"id": 644, "title": "룸즈에이 포항점", "isWish": false, "distance": 0, "createdAt": "2023-10-31"}, "theme": {"id": 3069, "companyName": "룸즈에이 포항점", "title": "안개꽃", "category": "드라마", "time": 60, "thumbnail": "https://roomescape-backend-image.s3.ap-northeast-2.amazonaws.com/theme/c2c7d014-b552-4879-9c9d-540abac5f74c.jpg", "isWish": false, "isReview": false, "address": "경북 포항시 북구 중앙로 273", "addressDetail": "5층"}, "comments": [], "likeCount": 0, "isLike": false, "reportCount": 0}, {"id": 376110, "themeId": 3069, "userId": 9257, "reviewLevel": 2, "userName": "솔대장", "playDate": "2021-09-27", "grade": 4, "level": "보통", "success": "성공", "extraTime": null, "remainingTime": null, "userHint": null, "content": "갬성 충 만,,,, 요즘 새로 나온 백예린 산책 들을때마다 안개꽃 생각나요,, 할 때보다 지나고 나서 더 기억에 남아요 커플 추천~!!", "isGrade": true, "createdAt": "09/27", "company": {"id": 644, "title": "룸즈에이 포항점", "isWish": false, "distance": 0, "createdAt": "2023-10-31"}, "theme": {"id": 3069, "companyName": "룸즈에이 포항점", "title": "안개꽃", "category": "드라마", "time": 60, "thumbnail": "https://roomescape-backend-image.s3.ap-northeast-2.amazonaws.com/theme/c2c7d014-b552-4879-9c9d-540abac5f74c.jpg", "isWish": false, "isReview": false, "address": "경북 포항시 북구 중앙로 273", "addressDetail": "5층"}, "comments": [], "likeCount": 0, "isLike": false, "reportCount": 0}, {"id": 366019, "themeId": 3069, "userId": 9487, "reviewLevel": 2, "userName": "아기공룡둘리", "playDate": "2021-09-12", "grade": 4, "level": "보통", "success": "성공", "extraTime": "10:00", "remainingTime": "50:00", "userHint": 2, "content": "#6 (3인) \n미술관 느낌의 테마, 스토리도 괜찮고 인테리어도 괜찮은데 나레이션이 아쉽… \n그래도 적당한 문제 난이도여서 여유롭게 문제 풀면서 탈출", "isGrade": true, "createdAt": "09/12", "company": {"id": 644, "title": "룸즈에이 포항점", "isWish": false, "distance": 0, "createdAt": "2023-10-31"}, "theme": {"id": 3069, "companyName": "룸즈에이 포항점", "title": "안개꽃", "category": "드라마", "time": 60, "thumbnail": "https://roomescape-backend-image.s3.ap-northeast-2.amazonaws.com/theme/c2c7d014-b552-4879-9c9d-540abac5f74c.jpg", "isWish": false, "isReview": false, "address": "경북 포항시 북구 중앙로 273", "addressDetail": "5층"}, "comments": [], "likeCount": 0, "isLike": false, "reportCount": 0}, {"id": 269158, "themeId": 3069, "userId": 3870, "reviewLevel": 6, "userName": "대구방탈홀릭", "playDate": "2021-03-27", "grade": 3, "level": "쉬움", "success": "성공", "extraTime": "19:20", "remainingTime": "40:40", "userHint": 0, "content": "한 문제에서 안 헤맸으면 30분 컷 나올정도로 볼륨이 아쉽다... 하지만 인테리어와 스토리는 감성 테마로 충분!! 그리고 특이한 진행 방식도 괜찮은 듯!!", "isGrade": true, "createdAt": "03/27", "company": {"id": 644, "title": "룸즈에이 포항점", "isWish": false, "distance": 0, "createdAt": "2023-10-31"}, "theme": {"id": 3069, "companyName": "룸즈에이 포항점", "title": "안개꽃", "category": "드라마", "time": 60, "thumbnail": "https://roomescape-backend-image.s3.ap-northeast-2.amazonaws.com/theme/c2c7d014-b552-4879-9c9d-540abac5f74c.jpg", "isWish": false, "isReview": false, "address": "경북 포항시 북구 중앙로 273", "addressDetail": "5층"}, "comments": [], "likeCount": 0, "isLike": false, "reportCount": 0}, {"id": 252297, "themeId": 3069, "userId": 3311, "reviewLevel": 4, "userName": "방울", "playDate": "2021-02-28", "grade": 3.5, "level": "보통", "success": "실패", "extraTime": "00:00", "remainingTime": "60:00", "userHint": null, "content": "(대학로점, 포항점 모두 진행) 마치 그 장소에 온 것 같아서, 나도 모르게 핸드폰을 찾았다 근데 음성이 몰입 다 깸.. 제가 읽을게요 그냥 한 문제 너무 어려웠다", "isGrade": true, "createdAt": "02/28", "company": {"id": 644, "title": "룸즈에이 포항점", "isWish": false, "distance": 0, "createdAt": "2023-10-31"}, "theme": {"id": 3069, "companyName": "룸즈에이 포항점", "title": "안개꽃", "category": "드라마", "time": 60, "thumbnail": "https://roomescape-backend-image.s3.ap-northeast-2.amazonaws.com/theme/c2c7d014-b552-4879-9c9d-540abac5f74c.jpg", "isWish": false, "isReview": false, "address": "경북 포항시 북구 중앙로 273", "addressDetail": "5층"}, "comments": [], "likeCount": 0, "isLike": false, "reportCount": 0}, {"id": 244966, "themeId": 3069, "userId": 6547, "reviewLevel": 3, "userName": "할배형", "playDate": "2021-02-16", "grade": 2.5, "level": "어려움", "success": "성공", "extraTime": null, "remainingTime": null, "userHint": null, "content": ".", "isGrade": true, "createdAt": "02/16", "company": {"id": 644, "title": "룸즈에이 포항점", "isWish": false, "distance": 0, "createdAt": "2023-10-31"}, "theme": {"id": 3069, "companyName": "룸즈에이 포항점", "title": "안개꽃", "category": "드라마", "time": 60, "thumbnail": "https://roomescape-backend-image.s3.ap-northeast-2.amazonaws.com/theme/c2c7d014-b552-4879-9c9d-540abac5f74c.jpg", "isWish": false, "isReview": false, "address": "경북 포항시 북구 중앙로 273", "addressDetail": "5층"}, "comments": [], "likeCount": 0, "isLike": false, "reportCount": 0}, {"id": 244917, "themeId": 3069, "userId": 6550, "reviewLevel": 2, "userName": "minizzang", "playDate": "2021-02-16", "grade": 3, "level": "보통", "success": "성공", "extraTime": null, "remainingTime": null, "userHint": null, "content": ".", "isGrade": true, "createdAt": "02/16", "company": {"id": 644, "title": "룸즈에이 포항점", "isWish": false, "distance": 0, "createdAt": "2023-10-31"}, "theme": {"id": 3069, "companyName": "룸즈에이 포항점", "title": "안개꽃", "category": "드라마", "time": 60, "thumbnail": "https://roomescape-backend-image.s3.ap-northeast-2.amazonaws.com/theme/c2c7d014-b552-4879-9c9d-540abac5f74c.jpg", "isWish": false, "isReview": false, "address": "경북 포항시 북구 중앙로 273", "addressDetail": "5층"}, "comments": [], "likeCount": 0, "isLike": false, "reportCount": 0}, {"id": 244091, "themeId": 3069, "userId": 6215, "reviewLevel": 4, "userName": "제한", "playDate": "2021-02-15", "grade": 1.5, "level": "쉬움", "success": "성공", "extraTime": "21:30", "remainingTime": "38:30", "userHint": 1, "content": "전체적으로 쉬운편. 방린이들끼리 가면 좋을 듯!", "isGrade": true, "createdAt": "02/15", "company": {"id": 644, "title": "룸즈에이 포항점", "isWish": false, "distance": 0, "createdAt": "2023-10-31"}, "theme": {"id": 3069, "companyName": "룸즈에이 포항점", "title": "안개꽃", "category": "드라마", "time": 60, "thumbnail": "https://roomescape-backend-image.s3.ap-northeast-2.amazonaws.com/theme/c2c7d014-b552-4879-9c9d-540abac5f74c.jpg", "isWish": false, "isReview": false, "address": "경북 포항시 북구 중앙로 273", "addressDetail": "5층"}, "comments": [], "likeCount": 0, "isLike": false, "reportCount": 0}, {"id": 239188, "themeId": 3069, "userId": 5231, "reviewLevel": 7, "userName": "응뵤이", "playDate": "2021-02-08", "grade": 4, "level": "보통", "success": "성공", "extraTime": null, "remainingTime": null, "userHint": null, "content": "재밌었다", "isGrade": true, "createdAt": "02/08", "company": {"id": 644, "title": "룸즈에이 포항점", "isWish": false, "distance": 0, "createdAt": "2023-10-31"}, "theme": {"id": 3069, "companyName": "룸즈에이 포항점", "title": "안개꽃", "category": "드라마", "time": 60, "thumbnail": "https://roomescape-backend-image.s3.ap-northeast-2.amazonaws.com/theme/c2c7d014-b552-4879-9c9d-540abac5f74c.jpg", "isWish": false, "isReview": false, "address": "경북 포항시 북구 중앙로 273", "addressDetail": "5층"}, "comments": [], "likeCount": 0, "isLike": false, "reportCount": 0}, {"id": 214235, "themeId": 3069, "userId": 4119, "reviewLevel": 4, "userName": "illiiilllilll", "playDate": "2020-12-20", "grade": 2.5, "level": "보통", "success": "성공", "extraTime": null, "remainingTime": null, "userHint": null, "content": "낫마이스타일", "isGrade": true, "createdAt": "12/20", "company": {"id": 644, "title": "룸즈에이 포항점", "isWish": false, "distance": 0, "createdAt": "2023-10-31"}, "theme": {"id": 3069, "companyName": "룸즈에이 포항점", "title": "안개꽃", "category": "드라마", "time": 60, "thumbnail": "https://roomescape-backend-image.s3.ap-northeast-2.amazonaws.com/theme/c2c7d014-b552-4879-9c9d-540abac5f74c.jpg", "isWish": false, "isReview": false, "address": "경북 포항시 북구 중앙로 273", "addressDetail": "5층"}, "comments": [], "likeCount": 0, "isLike": false, "reportCount": 0}, {"id": 195466, "themeId": 3069, "userId": 4619, "reviewLevel": 5, "userName": "우우웅", "playDate": "2020-11-13", "grade": 0, "level": "쉬움", "success": "성공", "extraTime": "12:00", "remainingTime": "48:00", "userHint": 1, "content": "2인", "isGrade": false, "createdAt": "11/13", "company": {"id": 644, "title": "룸즈에이 포항점", "isWish": false, "distance": 0, "createdAt": "2023-10-31"}, "theme": {"id": 3069, "companyName": "룸즈에이 포항점", "title": "안개꽃", "category": "드라마", "time": 60, "thumbnail": "https://roomescape-backend-image.s3.ap-northeast-2.amazonaws.com/theme/c2c7d014-b552-4879-9c9d-540abac5f74c.jpg", "isWish": false, "isReview": false, "address": "경북 포항시 북구 중앙로 273", "addressDetail": "5층"}, "comments": [], "likeCount": 0, "isLike": false, "reportCount": 0}, {"id": 269020, "themeId": 3069, "userId": 5696, "reviewLevel": 4, "userName": "코?코", "playDate": "2020-10-17", "grade": 3, "level": "쉬움", "success": "성공", "extraTime": null, "remainingTime": null, "userHint": null, "content": ".", "isGrade": true, "createdAt": "10/17", "company": {"id": 644, "title": "룸즈에이 포항점", "isWish": false, "distance": 0, "createdAt": "2023-10-31"}, "theme": {"id": 3069, "companyName": "룸즈에이 포항점", "title": "안개꽃", "category": "드라마", "time": 60, "thumbnail": "https://roomescape-backend-image.s3.ap-northeast-2.amazonaws.com/theme/c2c7d014-b552-4879-9c9d-540abac5f74c.jpg", "isWish": false, "isReview": false, "address": "경북 포항시 북구 중앙로 273", "addressDetail": "5층"}, "comments": [], "likeCount": 0, "isLike": false, "reportCount": 0}, {"id": 152020, "themeId": 3069, "userId": 4522, "reviewLevel": 2, "userName": "찡", "playDate": "2020-08-23", "grade": 3, "level": "보통", "success": "성공", "extraTime": "17:18", "remainingTime": "42:42", "userHint": 3, "content": "#5#2명#동그리 무난한테마, 처음에는 문제의도 파악못함", "isGrade": true, "createdAt": "08/23", "company": {"id": 644, "title": "룸즈에이 포항점", "isWish": false, "distance": 0, "createdAt": "2023-10-31"}, "theme": {"id": 3069, "companyName": "룸즈에이 포항점", "title": "안개꽃", "category": "드라마", "time": 60, "thumbnail": "https://roomescape-backend-image.s3.ap-northeast-2.amazonaws.com/theme/c2c7d014-b552-4879-9c9d-540abac5f74c.jpg", "isWish": false, "isReview": false, "address": "경북 포항시 북구 중앙로 273", "addressDetail": "5층"}, "comments": [], "likeCount": 0, "isLike": false, "reportCount": 0}, {"id": 151884, "themeId": 3069, "userId": 4447, "reviewLevel": 4, "userName": "일라", "playDate": "2020-08-22", "grade": 3, "level": "보통", "success": "성공", "extraTime": "17:18", "remainingTime": "42:42", "userHint": 3, "content": "생소한 문제 유형이 있었어요 ㅋㅋ", "isGrade": true, "createdAt": "08/22", "company": {"id": 644, "title": "룸즈에이 포항점", "isWish": false, "distance": 0, "createdAt": "2023-10-31"}, "theme": {"id": 3069, "companyName": "룸즈에이 포항점", "title": "안개꽃", "category": "드라마", "time": 60, "thumbnail": "https://roomescape-backend-image.s3.ap-northeast-2.amazonaws.com/theme/c2c7d014-b552-4879-9c9d-540abac5f74c.jpg", "isWish": false, "isReview": false, "address": "경북 포항시 북구 중앙로 273", "addressDetail": "5층"}, "comments": [], "likeCount": 0, "isLike": false, "reportCount": 0}]}